pyrax/__init__.py
pyrax/autoscale.py
pyrax/base_identity.py
pyrax/client.py
pyrax/cloudblockstorage.py
pyrax/cloudcdn.py
pyrax/clouddatabases.py
pyrax/clouddns.py
pyrax/cloudloadbalancers.py
pyrax/cloudmonitoring.py
pyrax/cloudnetworks.py
pyrax/exceptions.py
pyrax/fakes.py
pyrax/http.py
pyrax/image.py
pyrax/manager.py
pyrax/object_storage.py
pyrax/queueing.py
pyrax/resource.py
pyrax/service_catalog.py
pyrax/utils.py
pyrax/version.py
pyrax/__pycache__/__init__.cpython-39.opt-1.pyc
pyrax/__pycache__/autoscale.cpython-39.opt-1.pyc
pyrax/__pycache__/base_identity.cpython-39.opt-1.pyc
pyrax/__pycache__/client.cpython-39.opt-1.pyc
pyrax/__pycache__/cloudblockstorage.cpython-39.opt-1.pyc
pyrax/__pycache__/cloudcdn.cpython-39.opt-1.pyc
pyrax/__pycache__/clouddatabases.cpython-39.opt-1.pyc
pyrax/__pycache__/clouddns.cpython-39.opt-1.pyc
pyrax/__pycache__/cloudloadbalancers.cpython-39.opt-1.pyc
pyrax/__pycache__/cloudmonitoring.cpython-39.opt-1.pyc
pyrax/__pycache__/cloudnetworks.cpython-39.opt-1.pyc
pyrax/__pycache__/exceptions.cpython-39.opt-1.pyc
pyrax/__pycache__/fakes.cpython-39.opt-1.pyc
pyrax/__pycache__/http.cpython-39.opt-1.pyc
pyrax/__pycache__/image.cpython-39.opt-1.pyc
pyrax/__pycache__/manager.cpython-39.opt-1.pyc
pyrax/__pycache__/object_storage.cpython-39.opt-1.pyc
pyrax/__pycache__/queueing.cpython-39.opt-1.pyc
pyrax/__pycache__/resource.cpython-39.opt-1.pyc
pyrax/__pycache__/service_catalog.cpython-39.opt-1.pyc
pyrax/__pycache__/utils.cpython-39.opt-1.pyc
pyrax/__pycache__/version.cpython-39.opt-1.pyc
pyrax/identity/__init__.py
pyrax/identity/keystone_identity.py
pyrax/identity/rax_identity.py
pyrax/identity/__pycache__/__init__.cpython-39.opt-1.pyc
pyrax/identity/__pycache__/keystone_identity.cpython-39.opt-1.pyc
pyrax/identity/__pycache__/rax_identity.cpython-39.opt-1.pyc
pyrax-1.10.0.dist-info/LICENSE
pyrax-1.10.0.dist-info/METADATA
pyrax-1.10.0.dist-info/WHEEL
pyrax-1.10.0.dist-info/top_level.txt
pyrax-1.10.0.dist-info/RECORD
