Metadata-Version: 1.1
Name: pyrax
Version: 1.10.0
Summary: Python language bindings for OpenStack Clouds.
Home-page: https://github.com/pycontribs/pyrax
Author: Rackspace
Author-email: UNKNOWN
License: Apache License, Version 2.0
Keywords: pyrax rackspace cloud openstack
Platform: UNKNOWN
Classifier: Development Status :: 5 - Production/Stable
Classifier: License :: OSI Approved :: Apache Software License
Classifier: Programming Language :: Python
Classifier: Programming Language :: Python :: 2
Classifier: Programming Language :: Python :: 2.7
Classifier: Programming Language :: Python :: 3
Classifier: Programming Language :: Python :: 3.5
Classifier: Programming Language :: Python :: 3.6
Classifier: Programming Language :: Python :: 3.7
Classifier: Operating System :: OS Independent
